batcave/__init__.py
batcave/automation.py
batcave/cloudmgr.py
batcave/cms.py
batcave/commander.py
batcave/configmgr.py
batcave/data.py
batcave/expander.py
batcave/fileutil.py
batcave/gui.py
batcave/iispy.py
batcave/k8s.py
batcave/lang.py
batcave/menu.py
batcave/netutil.py
batcave/platarch.py
batcave/py.typed
batcave/qbpy.py
batcave/reporter.py
batcave/servermgr.py
batcave/serverpath.py
batcave/statemachine.py
batcave/sysutil.py
batcave/tcpy.py
batcave/time.py
batcave/version.py
batcave-46.0.0.dist-info/licenses/LICENSE
batcave-46.0.0.dist-info/WHEEL
batcave-46.0.0.dist-info/METADATA
batcave-46.0.0.dist-info/RECORD
